{
  "description": "Chris McN discusses the evolution of Saber, a leading DeFi application on Solana, highlighting its rapid growth and the team's strategic decisions. He emphasizes the importance of collaboration within the ecosystem and the potential for future innovations.",
  "topic_summary": "The talk covers the journey of Saber from its inception to becoming a major player in the DeFi space on Solana, including insights on partnerships and market dynamics [t=0:00-9:00].",
  "router_tags": [
    "DeFi",
    "Saber",
    "Solana",
    "Blockchain",
    "Cryptocurrency"
  ],
  "aliases": [
    "@SolanaFndn",
    "Solana Foundation",
    "SolanaFndn"
  ],
  "canonical_entities": [
    "$SOL",
    "@ChrisMcn",
    "@Saber"
  ],
  "is_explainer": false,
  "router_boost": 1.5
}